tacit/__init__.py
tacit-0.1.0.dist-info/WHEEL
tacit-0.1.0.dist-info/entry_points.txt
tacit-0.1.0.dist-info/METADATA
tacit-0.1.0.dist-info/RECORD
