Metadata-Version: 2.3
Name: tacit
Version: 0.1.0
Summary: A library for explicit data pipelines
Author: Alvaro Clemente
Author-email: Alvaro Clemente <clemente.varo@gmail.com>
Requires-Dist: pandera>=0.26.1
Requires-Dist: polars>=1.35.1
Requires-Python: >=3.13
